coralnet_toolbox/QtAnimationManager.py
coralnet_toolbox/QtAnnotationWindow.py
coralnet_toolbox/QtBatchInference.py
coralnet_toolbox/QtConfidenceWindow.py
coralnet_toolbox/QtEventFilter.py
coralnet_toolbox/QtImageWindow.py
coralnet_toolbox/QtLabelWindow.py
coralnet_toolbox/QtMainWindow.py
coralnet_toolbox/QtPatchSampling.py
coralnet_toolbox/QtProgressBar.py
coralnet_toolbox/QtRunner.py
coralnet_toolbox/QtSystemMonitor.py
coralnet_toolbox/QtTimer.py
coralnet_toolbox/QtVideoPlayer.py
coralnet_toolbox/QtWorkArea.py
coralnet_toolbox/__init__.py
coralnet_toolbox/main.py
coralnet_toolbox/utilities.py
coralnet_toolbox/Annotations/QtAnnotation.py
coralnet_toolbox/Annotations/QtMaskAnnotation.py
coralnet_toolbox/Annotations/QtMultiPolygonAnnotation.py
coralnet_toolbox/Annotations/QtPatchAnnotation.py
coralnet_toolbox/Annotations/QtPolygonAnnotation.py
coralnet_toolbox/Annotations/QtRectangleAnnotation.py
coralnet_toolbox/Annotations/__init__.py
coralnet_toolbox/BreakTime/QtBreakout.py
coralnet_toolbox/BreakTime/QtLightCycle.py
coralnet_toolbox/BreakTime/QtSnake.py
coralnet_toolbox/BreakTime/__init__.py
coralnet_toolbox/Common/QtMarginInput.py
coralnet_toolbox/Common/QtOverlapInput.py
coralnet_toolbox/Common/QtThresholdsWidget.py
coralnet_toolbox/Common/QtTileSizeInput.py
coralnet_toolbox/Common/QtUpdateImagePaths.py
coralnet_toolbox/Common/QtZChannelImport.py
coralnet_toolbox/Common/__init__.py
coralnet_toolbox/CoralNet/QtAuthenticate.py
coralnet_toolbox/CoralNet/QtDownload.py
coralnet_toolbox/CoralNet/__init__.py
coralnet_toolbox/Explorer/QtDataItem.py
coralnet_toolbox/Explorer/QtExplorer.py
coralnet_toolbox/Explorer/QtFeatureStore.py
coralnet_toolbox/Explorer/QtSettingsWidgets.py
coralnet_toolbox/Explorer/QtViewers.py
coralnet_toolbox/Explorer/__init__.py
coralnet_toolbox/Explorer/transformer_models.py
coralnet_toolbox/Explorer/yolo_models.py
coralnet_toolbox/IO/QtExportAnnotations.py
coralnet_toolbox/IO/QtExportCoralNetAnnotations.py
coralnet_toolbox-0.0.100.dist-info/licenses/LICENSE.txt
coralnet_toolbox-0.0.100.dist-info/METADATA
coralnet_toolbox-0.0.100.dist-info/WHEEL
coralnet_toolbox-0.0.100.dist-info/entry_points.txt
coralnet_toolbox-0.0.100.dist-info/top_level.txt
coralnet_toolbox-0.0.100.dist-info/RECORD
