Metadata-Version: 2.4
Name: coralnet-toolbox
Version: 0.0.100
Summary: Tools for annotating and developing ML models for benthic imagery
Author-email: Jordan Pierce <jordan.pierce@noaa.gov>
License: MIT License
Project-URL: Homepage, https://github.com/Jordan-Pierce/CoralNet-Toolbox
Keywords: CoralNet-Toolbox
Classifier: Intended Audience :: Developers
Classifier: License :: OSI Approved :: MIT License
Classifier: Natural Language :: English
Classifier: Programming Language :: Python :: 3.10
Requires-Python: <3.11,>=3.10
License-File: LICENSE.txt
Requires-Dist: PyQt5>=5.15.11
Requires-Dist: pyqtdarktheme
Requires-Dist: pyqtgraph
Requires-Dist: ultralytics>=8.3.191
Requires-Dist: segmentation-models-pytorch
Requires-Dist: albumentations
Requires-Dist: lap>=0.5.12
Requires-Dist: open-clip-torch>=2.20.0
Requires-Dist: supervision>=0.24.0
Requires-Dist: scikit-learn
Requires-Dist: scikit-image
Requires-Dist: umap-learn
Requires-Dist: faiss-cpu
Requires-Dist: pycocotools
Requires-Dist: ujson
Requires-Dist: timm==0.9.2
Requires-Dist: autodistill
Requires-Dist: transformers>=4.56.0
Requires-Dist: hf_xet
Requires-Dist: x-segment-anything>=0.0.8
Requires-Dist: yolo-tiling>=0.0.27
Requires-Dist: roboflow
Requires-Dist: rasterio
Requires-Dist: requests
Requires-Dist: selenium>=4.15.2
Requires-Dist: beautifulsoup4>=4.12.2
Requires-Dist: webdriver_manager
Requires-Dist: dill
Requires-Dist: seaborn
Requires-Dist: GPUtil
Requires-Dist: psutil
Provides-Extra: all
Requires-Dist: coralnet-toolbox[extra]; extra == "all"
Dynamic: license-file
